GandiApiLiveDNS/__init__.py
GandiApiLiveDNS/gandi.py
gandi_api_livedns_flexy2dd-0.0.1.dist-info/LICENSE
gandi_api_livedns_flexy2dd-0.0.1.dist-info/METADATA
gandi_api_livedns_flexy2dd-0.0.1.dist-info/WHEEL
gandi_api_livedns_flexy2dd-0.0.1.dist-info/top_level.txt
gandi_api_livedns_flexy2dd-0.0.1.dist-info/RECORD
