Metadata-Version: 2.1
Name: gandi-api-livedns-flexy2dd
Version: 0.0.1
Summary: Simple connector to Gandi.net live dns API
Home-page: https://github.com/flexy2dd/gandi-api-livedns
Author: Flexy2dd
Author-email: flexy2dd@blackdev.com
License: UNKNOWN
Platform: UNKNOWN
Classifier: Programming Language :: Python :: 3
Classifier: License :: OSI Approved :: MIT License
Classifier: Operating System :: OS Independent
Requires-Python: >=3.6
License-File: LICENSE
